odoo9_addon_product_multi_category-9.0.1.0.0-py2.7-nspkg.pth
odoo_addons/product_multi_category/__openerp__.py
odoo_addons/product_multi_category/__init__.py
odoo_addons/product_multi_category/README.rst
odoo_addons/product_multi_category/models/product.py
odoo_addons/product_multi_category/models/__init__.py
odoo_addons/product_multi_category/i18n/es.po
odoo_addons/product_multi_category/i18n/tr.po
odoo_addons/product_multi_category/i18n/ca.po
odoo_addons/product_multi_category/i18n/fr.po
odoo_addons/product_multi_category/i18n/product_m2mcategories.pot
odoo_addons/product_multi_category/i18n/sv.po
odoo_addons/product_multi_category/i18n/fr_BE.po
odoo_addons/product_multi_category/views/product_view.xml
odoo_addons/product_multi_category/static/description/icon.png
odoo9_addon_product_multi_category-9.0.1.0.0.dist-info/top_level.txt
odoo9_addon_product_multi_category-9.0.1.0.0.dist-info/WHEEL
odoo9_addon_product_multi_category-9.0.1.0.0.dist-info/RECORD
odoo9_addon_product_multi_category-9.0.1.0.0.dist-info/metadata.json
odoo9_addon_product_multi_category-9.0.1.0.0.dist-info/DESCRIPTION.rst
odoo9_addon_product_multi_category-9.0.1.0.0.dist-info/METADATA
odoo9_addon_product_multi_category-9.0.1.0.0.dist-info/namespace_packages.txt
